article_to_podcast/__init__.py
article_to_podcast/__main__.py
article_to_podcast/article.py
article_to_podcast/chunks.py
article_to_podcast/cli.py
article_to_podcast/common.py
article_to_podcast/filename.py
article_to_podcast/main.py
article_to_podcast-0.1.13.dist-info/LICENSE.md
article_to_podcast-0.1.13.dist-info/METADATA
article_to_podcast-0.1.13.dist-info/WHEEL
article_to_podcast-0.1.13.dist-info/entry_points.txt
article_to_podcast-0.1.13.dist-info/top_level.txt
article_to_podcast-0.1.13.dist-info/RECORD
